juhe/__init__.py
juhe-0.1.1.data/data/README.md/README.md
juhe-0.1.1.dist-info/LICENSE
juhe-0.1.1.dist-info/METADATA
juhe-0.1.1.dist-info/WHEEL
juhe-0.1.1.dist-info/entry_points.txt
juhe-0.1.1.dist-info/top_level.txt
juhe-0.1.1.dist-info/RECORD
